mdmenu/__init__.py
mdmenu/__main__.py
mdmenu/mdmenu.py
mdmenu-0.0.2.dist-info/licenses/LICENSE
mdmenu-0.0.2.dist-info/METADATA
mdmenu-0.0.2.dist-info/WHEEL
mdmenu-0.0.2.dist-info/top_level.txt
mdmenu-0.0.2.dist-info/RECORD
