Metadata-Version: 2.4
Name: mdmenu
Version: 0.0.2
Summary: A customisable text driven menu system.
Author-email: Matt Dennett <dennett.matthew+mdmenu@gmail.com>
License-Expression: GPL-3.0-or-later
Project-URL: Homepage, https://github.com/matthewdennett/python-mdmenu
Project-URL: Issues, https://github.com/matthewdennett/python-mdmenu/issues
Classifier: Operating System :: OS Independent
Classifier: Programming Language :: Python
Classifier: Programming Language :: Python :: 3
Classifier: Programming Language :: Python :: 3.9
Classifier: Programming Language :: Python :: 3.10
Classifier: Programming Language :: Python :: 3.11
Classifier: Programming Language :: Python :: 3.12
Requires-Python: >=3.9
License-File: LICENSE
Dynamic: license-file
